xaero/__main__.py
xaero/charger.py
xaero/config.py
xaero/constraints.py
xaero/mylog.py
xaero/ocpp_payload_reader.py
xaero/ocpp_server.py
xaero/test_conn.py
xaero/time_tools.py
xaero/ocpp15/base.py
xaero/ocpp15/types.py
xaero/soap/soap.py
xaero/soap/soap_build.py
xaero/soap/soap_parse.py
xaero/soap/soap_worker.py
xaero/ws/ws_worker.py
xaero-0.0.3.dist-info/METADATA
xaero-0.0.3.dist-info/WHEEL
xaero-0.0.3.dist-info/top_level.txt
xaero-0.0.3.dist-info/RECORD
