Metadata-Version: 2.1
Name: xaero
Version: 0.0.3
Summary: EVChager Simulation
Home-page: UNKNOWN
Author: Vinogradov D
Author-email: dgrapes@gmail.com
License: MIT
Platform: UNKNOWN
Classifier: Programming Language :: Python :: 3
Classifier: License :: OSI Approved :: MIT License
Classifier: Operating System :: OS Independent
Requires-Dist: requests
Requires-Dist: autobahn
